stdnum/__init__.py
stdnum/bic.py
stdnum/bitcoin.py
stdnum/casrn.py
stdnum/cusip.py
stdnum/damm.py
stdnum/ean.py
stdnum/exceptions.py
stdnum/figi.py
stdnum/grid.py
stdnum/gs1_128.py
stdnum/gs1_ai.dat
stdnum/iban.dat
stdnum/iban.py
stdnum/imei.py
stdnum/imo.py
stdnum/imsi.dat
stdnum/imsi.py
stdnum/isan.py
stdnum/isbn.dat
stdnum/isbn.py
stdnum/isil.dat
stdnum/isil.py
stdnum/isin.py
stdnum/ismn.py
stdnum/iso11649.py
stdnum/iso6346.py
stdnum/iso9362.py
stdnum/isrc.py
stdnum/issn.py
stdnum/lei.py
stdnum/luhn.py
stdnum/mac.py
stdnum/meid.py
stdnum/numdb.py
stdnum/oui.dat
stdnum/util.py
stdnum/vatin.py
stdnum/verhoeff.py
stdnum/ad/__init__.py
stdnum/ad/nrt.py
stdnum/al/__init__.py
stdnum/al/nipt.py
stdnum/ar/__init__.py
stdnum/ar/cbu.py
stdnum/ar/cuit.py
stdnum/ar/dni.py
stdnum/at/__init__.py
stdnum/at/businessid.py
stdnum/at/fa.dat
stdnum/at/postleitzahl.dat
stdnum/at/postleitzahl.py
stdnum/at/tin.py
stdnum/at/uid.py
stdnum/at/vnr.py
stdnum/au/__init__.py
stdnum/au/abn.py
stdnum/au/acn.py
stdnum/au/tfn.py
stdnum/be/__init__.py
stdnum/be/banks.dat
stdnum/be/iban.py
stdnum/be/vat.py
stdnum/bg/__init__.py
stdnum/bg/egn.py
stdnum/bg/pnf.py
stdnum/bg/vat.py
stdnum/br/__init__.py
stdnum/br/cnpj.py
stdnum/br/cpf.py
stdnum/by/__init__.py
stdnum/by/unp.py
stdnum/ca/__init__.py
stdnum/ca/bn.py
stdnum/ca/sin.py
stdnum/ch/__init__.py
stdnum/ch/esr.py
stdnum/ch/ssn.py
stdnum/ch/uid.py
stdnum/ch/vat.py
stdnum/cl/__init__.py
stdnum/cl/rut.py
stdnum/cn/__init__.py
stdnum/cn/loc.dat
stdnum/cn/ric.py
stdnum/cn/uscc.py
stdnum/co/__init__.py
stdnum/co/nit.py
stdnum/cr/__init__.py
stdnum/cr/cpf.py
stdnum/cr/cpj.py
stdnum/cr/cr.py
stdnum/cu/__init__.py
stdnum/cu/ni.py
stdnum/cy/__init__.py
stdnum/cy/vat.py
stdnum/cz/__init__.py
stdnum/cz/dic.py
stdnum/cz/rc.py
stdnum/de/__init__.py
stdnum/de/handelsregisternummer.py
stdnum/de/idnr.py
stdnum/de/stnr.py
stdnum/de/vat.py
stdnum/de/wkn.py
stdnum/dk/__init__.py
stdnum/dk/cpr.py
stdnum/dk/cvr.py
stdnum/do/__init__.py
stdnum/do/cedula.py
python_stdnum-1.17.dist-info/COPYING
python_stdnum-1.17.dist-info/METADATA
python_stdnum-1.17.dist-info/WHEEL
python_stdnum-1.17.dist-info/top_level.txt
python_stdnum-1.17.dist-info/RECORD
