Metadata-Version: 2.1
Name: python-stdnum
Version: 1.17
Summary: Python module to handle standardized numbers and codes
Home-page: https://arthurdejong.org/python-stdnum/
Author: Arthur de Jong
Author-email: arthur@arthurdejong.org
License: LGPL
Project-URL: Documentation, https://arthurdejong.org/python-stdnum/doc/
Project-URL: GitHub, https://github.com/arthurdejong/python-stdnum/
Platform: UNKNOWN
Classifier: Development Status :: 5 - Production/Stable
Classifier: Intended Audience :: Developers
Classifier: Intended Audience :: Financial and Insurance Industry
Classifier: Intended Audience :: Information Technology
Classifier: Intended Audience :: Telecommunications Industry
Classifier: License :: OSI Approved :: GNU Lesser General Public License v2 or later (LGPLv2+)
Classifier: Operating System :: OS Independent
Classifier: Programming Language :: Python
Classifier: Programming Language :: Python :: 2
Classifier: Programming Language :: Python :: 2.7
Classifier: Programming Language :: Python :: 3
Classifier: Programming Language :: Python :: 3.5
Classifier: Programming Language :: Python :: 3.6
Classifier: Programming Language :: Python :: 3.7
Classifier: Programming Language :: Python :: 3.8
Classifier: Programming Language :: Python :: 3.9
Classifier: Programming Language :: Python :: Implementation :: PyPy
Classifier: Topic :: Office/Business :: Financial
Classifier: Topic :: Software Development :: Libraries :: Python Modules
Classifier: Topic :: Text Processing :: General
Provides-Extra: SOAP
Provides-Extra: SOAP-ALT
Provides-Extra: SOAP-FALLBACK
